scrapster-1.0.6.dist-info/METADATA
scrapster-1.0.6.dist-info/WHEEL
scrapster/__init__.py
scrapster/scrapster.abi3.so
scrapster-1.0.6.dist-info/RECORD
