Metadata-Version: 2.4
Name: scrapster
Version: 1.0.6
Classifier: Programming Language :: Python
Classifier: Programming Language :: Rust
Classifier: Operating System :: POSIX :: Linux
Classifier: Operating System :: MacOS
Keywords: metrics,system,rust,pyo3
License: MIT
Requires-Python: >=3.8
Project-URL: Homepage, https://github.com/kemalcanbora/scrapster
